main.py
hjkslganbosfi-0.2.0.dist-info/METADATA
hjkslganbosfi-0.2.0.dist-info/WHEEL
hjkslganbosfi-0.2.0.dist-info/top_level.txt
hjkslganbosfi-0.2.0.dist-info/RECORD
