Metadata-Version: 2.1
Name: hjkslganbosfi
Version: 0.2.0
Summary: A brief description of your package
Author: hrewew
